{
  "easycom": {
    "^u-(.*)": "uview-ui/components/u-$1/u-$1.vue"
  },
  "pages": [
    {
      "path": "pages/index/index",
      "style": {
        "navigationBarTitleText": "lovemeal"
      }
    },
    {
      "path": "pages/user/login",
      "style": {
        "navigationBarTitleText": "用户登录"
      }
    },
    {
      "path": "pages/user/forget",
      "style": {
        "navigationBarTitleText": "密码重置"
      }
    },
    {
      "path": "pages/menu/index",
      "style": {
        "navigationBarTitleText": "菜品"
      }
    }, {
      "path": "pages/menu/foodDetail",
      "style": {
        "navigationBarTitleText": "菜品详情"
      }
    },
    {
      "path": "pages/order/index",
      "style": {
        "navigationBarTitleText": "订单"
      }
    },
    {
      "path": "pages/profile/index",
      "style": {
        "navigationBarTitleText": "我的"
      }
    }
  
  ],
  "globalStyle": {
    "navigationBarTextStyle": "black",
    "navigationBarTitleText": "uni-app",
    "navigationBarBackgroundColor": "#F8F8F8",
    "backgroundColor": "#F8F8F8"
  },
  "tabBar": {
    "list": [
      {
        "pagePath": "pages/index/index",
        "text": "首页",
        "iconPath": "/static/tabbarIcon/home.png",
        "selectedIconPath": "/static/tabbarIcon/home-fill.png"
      },
      {
        "pagePath": "pages/menu/index",
        "text": "菜品",
        "iconPath": "/static/tabbarIcon/cart-empty.png",
        "selectedIconPath": "/static/tabbarIcon/cart-empty-fill.png"
      },
      {
        "pagePath": "pages/order/index",
        "text": "订单",
       "iconPath": "/static/tabbarIcon/order.png",
        "selectedIconPath": "/static/tabbarIcon/order-inspection.png"
      },
      {
        "pagePath": "pages/profile/index",
        "text": "我的",
        "iconPath": "/static/tabbarIcon/customer.png",
        "selectedIconPath": "/static/tabbarIcon/customer-fill.png"
      }
    ]
  }
}
